embeddings/__init__.py
embeddings/_modidx.py
embeddings/config/__init__.py
embeddings/config/base_config.py
embeddings/config/config_space.py
embeddings/config/lighting_config_space.py
embeddings/config/lightning_config.py
embeddings/config/parameters.py
embeddings/data/__init__.py
embeddings/data/data_collator.py
embeddings/data/data_loader.py
embeddings/data/datamodule.py
embeddings/data/dataset.py
embeddings/data/io.py
embeddings/data/qa_datamodule.py
embeddings/defaults.py
embeddings/embedding/__init__.py
embeddings/embedding/embedding.py
embeddings/embedding/sklearn_embedding.py
embeddings/evaluator/__init__.py
embeddings/evaluator/evaluation_results.py
embeddings/evaluator/evaluator.py
embeddings/evaluator/leaderboard.py
embeddings/evaluator/metrics_evaluator.py
embeddings/evaluator/question_answering_evaluator.py
embeddings/evaluator/sequence_labeling_evaluator.py
embeddings/evaluator/submission.py
embeddings/evaluator/submission_utils.py
embeddings/evaluator/text_classification_evaluator.py
embeddings/metric/__init__.py
embeddings/metric/hugging_face_metric.py
embeddings/metric/lightning_seqeval_metric.py
embeddings/metric/metric.py
embeddings/metric/prfs_per_class_metric.py
embeddings/metric/question_answering.py
embeddings/metric/seqeval_metric.py
embeddings/metric/sequence_labeling.py
embeddings/metric/unit_seqeval_metric.py
embeddings/model/__init__.py
embeddings/model/base_model.py
embeddings/model/lightning_model.py
embeddings/model/lightning_module/__init__.py
embeddings/model/lightning_module/huggingface_module.py
embeddings/model/lightning_module/lightning_module.py
embeddings/model/lightning_module/question_answering.py
embeddings/model/lightning_module/sequence_labeling.py
embeddings/model/lightning_module/text_classification.py
embeddings/model/model.py
embeddings/model/sklearn_model.py
embeddings/pipeline/__init__.py
embeddings/pipeline/hf_preprocessing_pipeline.py
embeddings/pipeline/hps_pipeline.py
clarinpl_embeddings-0.0.1rc7078377068125.dist-info/LICENSE
clarinpl_embeddings-0.0.1rc7078377068125.dist-info/METADATA
clarinpl_embeddings-0.0.1rc7078377068125.dist-info/WHEEL
clarinpl_embeddings-0.0.1rc7078377068125.dist-info/RECORD
