Metadata-Version: 2.1
Name: clarinpl-embeddings
Version: 0.0.1rc7078377068125
Summary: 
Home-page: https://github.com/CLARIN-PL/embeddings
License: MIT
Author: Roman Bartusiak
Author-email: riomus@gmail.com
Requires-Python: >=3.8.0,<4.0
Classifier: License :: OSI Approved :: MIT License
Classifier: Programming Language :: Python :: 3
Classifier: Programming Language :: Python :: 3.8
Classifier: Programming Language :: Python :: 3.9
Classifier: Programming Language :: Python :: 3.10
Classifier: Programming Language :: Python :: 3.11
Provides-Extra: developer
Requires-Dist: Pillow (>=8.2.0)
Requires-Dist: annoy (>=1.17.0)
Requires-Dist: appdirs (>=1.4.4)
Requires-Dist: click (>=8.1.7,<9.0.0)
Requires-Dist: datasets (>=1.16.1)
Requires-Dist: evaluate (>=0.4.0)
Requires-Dist: fastapi (>=0.88)
Requires-Dist: intel-openmp (>=2022.0.3,<2023.0.0) ; sys_platform == "win32"
Requires-Dist: lightning (==2.0.1)
Requires-Dist: lz4 (>=3.1.10)
Requires-Dist: numpy (>=1.20.0,<=1.23.4)
Requires-Dist: onnx (>=1.13.1)
Requires-Dist: optuna (>=2.9.1)
Requires-Dist: pydantic (>=1.8.2)
Requires-Dist: requests (>=2.25.1)
Requires-Dist: sacremoses (>=0.0.53)
Requires-Dist: scikit-learn (>=1.0.0)
Requires-Dist: scipy (>=1.6.2)
Requires-Dist: seqeval (>=1.2.2)
Requires-Dist: setuptools (>=65.5.1)
Requires-Dist: srsly (>=2.4.1)
Requires-Dist: tensorboard (>=2.4.1)
Requires-Dist: tokenizers (>=0.13.2)
Requires-Dist: torch (==2.0.0)
Requires-Dist: torchmetrics (>=0.11.4)
Requires-Dist: transformers[onnx] (>=4.28.1)
Requires-Dist: typer (>=0.4.0)
Requires-Dist: types-PyYAML (>=5.4.10)
Requires-Dist: types-setuptools (>=57.4.11)
Requires-Dist: typing-extensions (>=4.0.1.0) ; extra == "developer"
Requires-Dist: wandb (>=0.12.10)
